Metadata-Version: 2.1
Name: quality-viewer
Version: 0.0.3
Summary: A simple CLI for rendering Quality Views
Home-page: https://github.com/DaMouse404/quality-viewer
Author: Chris Sidebottom
Author-email: chris@damouse.co.uk
License: UNKNOWN
Platform: any
Classifier: License :: OSI Approved :: MIT License
Classifier: Programming Language :: Python :: 3
